[
    {
        "0x169833EBB85FBD3cb67eeC73Ed02f738c0017951": [
            {
                "pool": "0x623de087b6fdac0577acde44ae8e76ed7b3bf98b",
                "feeFactor": "0.9975031223974601",
                "balAndRatioFactor": "1",
                "wrapFactor": "1",
                "valueUSD": "71.40380652983773118",
                "factorUSD": "71.225519964577287089"
            }
        ],
        "0x458cD345B4C05e8DF39d0A07220feb4Ec19F5e6f": [
            {
                "pool": "0x623de087b6fdac0577acde44ae8e76ed7b3bf98b",
                "feeFactor": "0.9975031223974601",
                "balAndRatioFactor": "1",
                "wrapFactor": "1",
                "valueUSD": "101255.704121958204839651",
                "factorUSD": "101002.881022206680366951"
            }
        ],
        "0x544F8DC8a81EA9978B0C8E7B94eb67fA66F4e881": [
            {
                "pool": "0x623de087b6fdac0577acde44ae8e76ed7b3bf98b",
                "feeFactor": "0.9975031223974601",
                "balAndRatioFactor": "1",
                "wrapFactor": "1",
                "valueUSD": "0.169021007713667528",
                "factorUSD": "0.168598982945148548"
            }
        ],
        "0x689cC0Ea1140546a8a7985315E9C8fef7e0461bc": [
            {
                "pool": "0x623de087b6fdac0577acde44ae8e76ed7b3bf98b",
                "feeFactor": "0.9975031223974601",
                "balAndRatioFactor": "1",
                "wrapFactor": "1",
                "valueUSD": "6934.292246762599696675",
                "factorUSD": "6916.978167762192080097"
            }
        ]
    },
    {
        "0x169833EBB85FBD3cb67eeC73Ed02f738c0017951": "0.000872587035674394",
        "0x458cD345B4C05e8DF39d0A07220feb4Ec19F5e6f": "1.237390819885522901",
        "0x544F8DC8a81EA9978B0C8E7B94eb67fA66F4e881": "0.000002065513692548",
        "0x689cC0Ea1140546a8a7985315E9C8fef7e0461bc": "0.084740209383291967"
    },
    {
        "0x9C58BAcC331c9aa871AFD802DB6379a98e80CEdb": "53995.626654458197495339",
        "0xC45b3C1c24d5F54E7a2cF288ac668c74Dd507a84": "53995.626654458197495339"
    }
]