[
    {
        "0x03c6592bC87E7fDF583B5337A0e344B832bcBdec": [
            {
                "pool": "0x5fa00d2ba520f95f548ff0813f9f74facdf1b807",
                "feeFactor": "0.9985947383062085",
                "balAndRatioFactor": "1",
                "wrapFactor": "1",
                "valueUSD": "19.039693639702918458",
                "factorUSD": "19.012937887569518285"
            }
        ],
        "0x05695FacB3337A65286B47F1d43f6737F3005c20": [
            {
                "pool": "0x5fa00d2ba520f95f548ff0813f9f74facdf1b807",
                "feeFactor": "0.9985947383062085",
                "balAndRatioFactor": "1",
                "wrapFactor": "1",
                "valueUSD": "2.977406913996732101",
                "factorUSD": "2.973222878113662531"
            }
        ],
        "0x05c1Ff33107b857c4FAa6F1425BA78e98Ab74E9d": [
            {
                "pool": "0x5fa00d2ba520f95f548ff0813f9f74facdf1b807",
                "feeFactor": "0.9985947383062085",
                "balAndRatioFactor": "1",
                "wrapFactor": "1",
                "valueUSD": "2.755100933149685185",
                "factorUSD": "2.751229295345800716"
            }
        ],
        "0x0b64Ebfb2694cF6dfEb6F5980Ed137849C5B246A": [
            {
                "pool": "0x5fa00d2ba520f95f548ff0813f9f74facdf1b807",
                "feeFactor": "0.9985947383062085",
                "balAndRatioFactor": "1",
                "wrapFactor": "1",
                "valueUSD": "6.726915117199258952",
                "factorUSD": "6.717462041067671875"
            }
        ],
        "0x0fDA4Ac09a12C10FAe30E429F4D6b47C9A83c87e": [
            {
                "pool": "0x5fa00d2ba520f95f548ff0813f9f74facdf1b807",
                "feeFactor": "0.9985947383062085",
                "balAndRatioFactor": "1",
                "wrapFactor": "1",
                "valueUSD": "191.058436200763337039",
                "factorUSD": "190.789949099094697112"
            }
        ],
        "0x126BbF0dc21fb51d93367560dAc2493bc5E1492a": [
            {
                "pool": "0x5fa00d2ba520f95f548ff0813f9f74facdf1b807",
                "feeFactor": "0.9985947383062085",
                "balAndRatioFactor": "1",
                "wrapFactor": "1",
                "valueUSD": "19.29283345174714415",
                "factorUSD": "19.265721971932704646"
            }
        ],
        "0x14602524171f1FF792cE532BeD1fB3ac6e2Fa9Df": [
            {
                "pool": "0x5fa00d2ba520f95f548ff0813f9f74facdf1b807",
                "feeFactor": "0.9985947383062085",
                "balAndRatioFactor": "1",
                "wrapFactor": "1",
                "valueUSD": "1.065415032766312361",
                "factorUSD": "1.063917845832776246"
            }
        ],
        "0x16894007836e9F29A4349EA4422aE26db64DEF0B": [
            {
                "pool": "0x5fa00d2ba520f95f548ff0813f9f74facdf1b807",
                "feeFactor": "0.9985947383062085",
                "balAndRatioFactor": "1",
                "wrapFactor": "1",
                "valueUSD": "3.571434354078073084",
                "factorUSD": "3.566415554188396179"
            }
        ],
        "0x169833EBB85FBD3cb67eeC73Ed02f738c0017951": [
            {
                "pool": "0x5fa00d2ba520f95f548ff0813f9f74facdf1b807",
                "feeFactor": "0.9985947383062085",
                "balAndRatioFactor": "1",
                "wrapFactor": "1",
                "valueUSD": "11.942626033787616427",
                "factorUSD": "11.925843518899057578"
            }
        ],
        "0x1Bec4f239F1Ec11FD8DC7B31A8fea7A5bA5a9Aa4": [
            {
                "pool": "0x5fa00d2ba520f95f548ff0813f9f74facdf1b807",
                "feeFactor": "0.9985947383062085",
                "balAndRatioFactor": "1",
                "wrapFactor": "1",
                "valueUSD": "352.076365546508527757",
                "factorUSD": "351.58160611671668587"
            }
        ],
        "0x1dCBB7863137b0928AC30D9e834fFe166c0772A0": [
            {
                "pool": "0x5fa00d2ba520f95f548ff0813f9f74facdf1b807",
                "feeFactor": "0.9985947383062085",
                "balAndRatioFactor": "1",
                "wrapFactor": "1",
                "valueUSD": "3.375671282697011777",
                "factorUSD": "3.370927581152605649"
            }
        ],
        "0x1DF6DB610036713fE15AAa1EAdF9DfCbB9F2d7B8": [
            {
                "pool": "0x5fa00d2ba520f95f548ff0813f9f74facdf1b807",
                "feeFactor": "0.9985947383062085",
                "balAndRatioFactor": "1",
                "wrapFactor": "1",
                "valueUSD": "3938.669698256198524398",
                "factorUSD": "3933.134836604741762646"
            }
        ],
        "0x1e81eED69C5357713084C96D88c1C4c413De6e7e": [
            {
                "pool": "0x5fa00d2ba520f95f548ff0813f9f74facdf1b807",
                "feeFactor": "0.9985947383062085",
                "balAndRatioFactor": "1",
                "wrapFactor": "1",
                "valueUSD": "111.067452457599357248",
                "factorUSD": "110.911373621233684276"
            }
        ],
        "0x2186473547fA23D3AB86dA9EC53fA56cC55C7e0E": [
            {
                "pool": "0x5fa00d2ba520f95f548ff0813f9f74facdf1b807",
                "feeFactor": "0.9985947383062085",
                "balAndRatioFactor": "1",
                "wrapFactor": "1",
                "valueUSD": "0.94762214775077192",
                "factorUSD": "0.946290490646349331"
            }
        ],
        "0x25aD2667B19e866109c1a93102b816730a6Aec3f": [
            {
                "pool": "0x5fa00d2ba520f95f548ff0813f9f74facdf1b807",
                "feeFactor": "0.9985947383062085",
                "balAndRatioFactor": "1",
                "wrapFactor": "1",
                "valueUSD": "4.443939912669324551",
                "factorUSD": "4.437695014140539205"
            }
        ],
        "0x266cA9F02E8395D7cC746CB6Ec986C2E06c75a28": [
            {
                "pool": "0x5fa00d2ba520f95f548ff0813f9f74facdf1b807",
                "feeFactor": "0.9985947383062085",
                "balAndRatioFactor": "1",
                "wrapFactor": "1",
                "valueUSD": "117.774443155930573981",
                "factorUSD": "117.608939242455920248"
            }
        ],
        "0x28440FecB243B268E1484e72ce98Bd866848E144": [
            {
                "pool": "0x5fa00d2ba520f95f548ff0813f9f74facdf1b807",
                "feeFactor": "0.9985947383062085",
                "balAndRatioFactor": "1",
                "wrapFactor": "1",
                "valueUSD": "19.293063716083867521",
                "factorUSD": "19.265951912687776174"
            }
        ],
        "0x28BAb5CECBd39870Db7daa7Ec29Ba219D0865804": [
            {
                "pool": "0x5fa00d2ba520f95f548ff0813f9f74facdf1b807",
                "feeFactor": "0.9985947383062085",
                "balAndRatioFactor": "1",
                "wrapFactor": "1",
                "valueUSD": "19.941180159371559343",
                "factorUSD": "19.913157582764599411"
            }
        ],
        "0x2949d0157Ef65a9226a4A0E0cFd0Ac52433520d9": [
            {
                "pool": "0x5fa00d2ba520f95f548ff0813f9f74facdf1b807",
                "feeFactor": "0.9985947383062085",
                "balAndRatioFactor": "1",
                "wrapFactor": "1",
                "valueUSD": "176.343000914114417184",
                "factorUSD": "176.095192849961572725"
            }
        ],
        "0x29f46A92078f6011A47dF128aF735208782579bF": [
            {
                "pool": "0x5fa00d2ba520f95f548ff0813f9f74facdf1b807",
                "feeFactor": "0.9985947383062085",
                "balAndRatioFactor": "1",
                "wrapFactor": "1",
                "valueUSD": "0.952247105041632442",
                "factorUSD": "0.950908948661893585"
            }
        ],
        "0x2C982f6926B66b9CCB9999D527De55c74697bba5": [
            {
                "pool": "0x5fa00d2ba520f95f548ff0813f9f74facdf1b807",
                "feeFactor": "0.9985947383062085",
                "balAndRatioFactor": "1",
                "wrapFactor": "1",
                "valueUSD": "6.400550714956515376",
                "factorUSD": "6.391556266217617187"
            }
        ],
        "0x32BcCA9f63aBE93195689f6Af28B5677c39C8356": [
            {
                "pool": "0x5fa00d2ba520f95f548ff0813f9f74facdf1b807",
                "feeFactor": "0.9985947383062085",
                "balAndRatioFactor": "1",
                "wrapFactor": "1",
                "valueUSD": "2.212583621812465125",
                "factorUSD": "2.209474362804421608"
            }
        ],
        "0x34E467c9A3B3C5767539AB3Df5A49314d8DEB466": [
            {
                "pool": "0x5fa00d2ba520f95f548ff0813f9f74facdf1b807",
                "feeFactor": "0.9985947383062085",
                "balAndRatioFactor": "1",
                "wrapFactor": "1",
                "valueUSD": "13.709988950337506225",
                "factorUSD": "13.690722828043292192"
            }
        ],
        "0x366b862656D5F06d506D6FC2C1e31425C2cCFC3f": [
            {
                "pool": "0x5fa00d2ba520f95f548ff0813f9f74facdf1b807",
                "feeFactor": "0.9985947383062085",
                "balAndRatioFactor": "1",
                "wrapFactor": "1",
                "valueUSD": "10.44320743371397877",
                "factorUSD": "10.428531994347061881"
            }
        ],
        "0x38376A546C30bd84146f7e4C08cC596DF8aa10C2": [
            {
                "pool": "0x5fa00d2ba520f95f548ff0813f9f74facdf1b807",
                "feeFactor": "0.9985947383062085",
                "balAndRatioFactor": "1",
                "wrapFactor": "1",
                "valueUSD": "21.806877522455560994",
                "factorUSD": "21.776233152812051303"
            }
        ],
        "0x3b43e78D75903CB755AF4fC94fA7348b49d5F460": [
            {
                "pool": "0x5fa00d2ba520f95f548ff0813f9f74facdf1b807",
                "feeFactor": "0.9985947383062085",
                "balAndRatioFactor": "1",
                "wrapFactor": "1",
                "valueUSD": "44.560717630383713453",
                "factorUSD": "44.498098160849875679"
            }
        ],
        "0x43d1eb966d0ADfe9E5C0d3Cff1223bed0823225C": [
            {
                "pool": "0x5fa00d2ba520f95f548ff0813f9f74facdf1b807",
                "feeFactor": "0.9985947383062085",
                "balAndRatioFactor": "1",
                "wrapFactor": "1",
                "valueUSD": "0.710553377183403961",
                "factorUSD": "0.709554863741053941"
            }
        ],
        "0x44909bDd05ddA8A13c681414Cf684Bf148d5f411": [
            {
                "pool": "0x5fa00d2ba520f95f548ff0813f9f74facdf1b807",
                "feeFactor": "0.9985947383062085",
                "balAndRatioFactor": "1",
                "wrapFactor": "1",
                "valueUSD": "2.229471559778156413",
                "factorUSD": "2.226338568797802583"
            }
        ],
        "0x4598B7560f51D6325Ab0212d063012F720e97504": [
            {
                "pool": "0x5fa00d2ba520f95f548ff0813f9f74facdf1b807",
                "feeFactor": "0.9985947383062085",
                "balAndRatioFactor": "1",
                "wrapFactor": "1",
                "valueUSD": "18.877151004139201008",
                "factorUSD": "18.850623666945166439"
            }
        ],
        "0x49cADC6F25b9FA00D7dF4f3cE4caD7180f0BD2Ce": [
            {
                "pool": "0x5fa00d2ba520f95f548ff0813f9f74facdf1b807",
                "feeFactor": "0.9985947383062085",
                "balAndRatioFactor": "1",
                "wrapFactor": "1",
                "valueUSD": "19.293063716083867521",
                "factorUSD": "19.265951912687776174"
            }
        ],
        "0x4C89d3625f581dfa803fF7C102b99B72efDc500c": [
            {
                "pool": "0x5fa00d2ba520f95f548ff0813f9f74facdf1b807",
                "feeFactor": "0.9985947383062085",
                "balAndRatioFactor": "1",
                "wrapFactor": "1",
                "valueUSD": "28.962425324688245878",
                "factorUSD": "28.921725537820164639"
            }
        ],
        "0x4E0985E556069B3D69f4E76DB3e2B8D2B5047956": [
            {
                "pool": "0x5fa00d2ba520f95f548ff0813f9f74facdf1b807",
                "feeFactor": "0.9985947383062085",
                "balAndRatioFactor": "1",
                "wrapFactor": "1",
                "valueUSD": "15187.31733795922981123",
                "factorUSD": "15165.975182672740209108"
            }
        ],
        "0x507CC427C8Fba38b81E891549189E6718862Af45": [
            {
                "pool": "0x5fa00d2ba520f95f548ff0813f9f74facdf1b807",
                "feeFactor": "0.9985947383062085",
                "balAndRatioFactor": "1",
                "wrapFactor": "1",
                "valueUSD": "1.143607381718900395",
                "factorUSD": "1.14200031407263363"
            }
        ],
        "0x51fF13A729c61ec0a10555F92028c4d07b16970b": [
            {
                "pool": "0x5fa00d2ba520f95f548ff0813f9f74facdf1b807",
                "feeFactor": "0.9985947383062085",
                "balAndRatioFactor": "1",
                "wrapFactor": "1",
                "valueUSD": "464.395366010242583114",
                "factorUSD": "463.742768991614106034"
            }
        ],
        "0x52b4Fab7FD9565011703e0dB38FF70882838E085": [
            {
                "pool": "0x5fa00d2ba520f95f548ff0813f9f74facdf1b807",
                "feeFactor": "0.9985947383062085",
                "balAndRatioFactor": "1",
                "wrapFactor": "1",
                "valueUSD": "536.279828061098118714",
                "factorUSD": "535.52621456157076558"
            }
        ],
        "0x56f386B8889Fc0FbAF0f5300937B3fe0e9064a8f": [
            {
                "pool": "0x5fa00d2ba520f95f548ff0813f9f74facdf1b807",
                "feeFactor": "0.9985947383062085",
                "balAndRatioFactor": "1",
                "wrapFactor": "1",
                "valueUSD": "38.426424342415503001",
                "factorUSD": "38.372425160257729265"
            }
        ],
        "0x57A07c76A8c5D497Db4BCaB8884869b0998ac726": [
            {
                "pool": "0x5fa00d2ba520f95f548ff0813f9f74facdf1b807",
                "feeFactor": "0.9985947383062085",
                "balAndRatioFactor": "1",
                "wrapFactor": "1",
                "valueUSD": "19.293063716083867521",
                "factorUSD": "19.265951912687776174"
            }
        ],
        "0x611dCd191690a60A4ed50021505882762c316Bc0": [
            {
                "pool": "0x5fa00d2ba520f95f548ff0813f9f74facdf1b807",
                "feeFactor": "0.9985947383062085",
                "balAndRatioFactor": "1",
                "wrapFactor": "1",
                "valueUSD": "19809.588102385995203701",
                "factorUSD": "19781.750447055924313759"
            }
        ],
        "0x646f535ABEBc5d9755c0101C3F813D76C0a1E0C8": [
            {
                "pool": "0x5fa00d2ba520f95f548ff0813f9f74facdf1b807",
                "feeFactor": "0.9985947383062085",
                "balAndRatioFactor": "1",
                "wrapFactor": "1",
                "valueUSD": "2.211804060828667201",
                "factorUSD": "2.20869589730781219"
            }
        ],
        "0x69acB25746533Cd28147eAfF75d001598374454f": [
            {
                "pool": "0x5fa00d2ba520f95f548ff0813f9f74facdf1b807",
                "feeFactor": "0.9985947383062085",
                "balAndRatioFactor": "1",
                "wrapFactor": "1",
                "valueUSD": "0.018652221111246812",
                "factorUSD": "0.018626009859415047"
            }
        ],
        "0x6C924AB13f2de31Ff1f9B0394933Ae0f5D4a7a21": [
            {
                "pool": "0x5fa00d2ba520f95f548ff0813f9f74facdf1b807",
                "feeFactor": "0.9985947383062085",
                "balAndRatioFactor": "1",
                "wrapFactor": "1",
                "valueUSD": "19.039693639702918458",
                "factorUSD": "19.012937887569518285"
            }
        ],
        "0x719450B5feD41e3ea88aCA1745Db525a841366Ac": [
            {
                "pool": "0x5fa00d2ba520f95f548ff0813f9f74facdf1b807",
                "feeFactor": "0.9985947383062085",
                "balAndRatioFactor": "1",
                "wrapFactor": "1",
                "valueUSD": "19.039693639702918458",
                "factorUSD": "19.012937887569518285"
            }
        ],
        "0x72F42Fa01716D6525B1385fb9aBD2Fd125785F30": [
            {
                "pool": "0x5fa00d2ba520f95f548ff0813f9f74facdf1b807",
                "feeFactor": "0.9985947383062085",
                "balAndRatioFactor": "1",
                "wrapFactor": "1",
                "valueUSD": "3.468623306742391587",
                "factorUSD": "3.4637489832792341"
            }
        ],
        "0x73692E42db099B426885b9fB5D4B46EA7fFD4DAa": [
            {
                "pool": "0x5fa00d2ba520f95f548ff0813f9f74facdf1b807",
                "feeFactor": "0.9985947383062085",
                "balAndRatioFactor": "1",
                "wrapFactor": "1",
                "valueUSD": "176.132253896668132966",
                "factorUSD": "175.884741987225986579"
            }
        ],
        "0x742F6A3589168856deF641FA29BBDb2B51B12488": [
            {
                "pool": "0x5fa00d2ba520f95f548ff0813f9f74facdf1b807",
                "feeFactor": "0.9985947383062085",
                "balAndRatioFactor": "1",
                "wrapFactor": "1",
                "valueUSD": "37.462379512766881542",
                "factorUSD": "37.409735065879310766"
            }
        ],
        "0x7560E255F7D5ABd4Af80D48f9834bad510A27835": [
            {
                "pool": "0x5fa00d2ba520f95f548ff0813f9f74facdf1b807",
                "feeFactor": "0.9985947383062085",
                "balAndRatioFactor": "1",
                "wrapFactor": "1",
                "valueUSD": "33.55661939531490326",
                "factorUSD": "33.509463563505526338"
            }
        ],
        "0x7C684BA5387688b2dF88A51F759aaD4A4b07Ccc5": [
            {
                "pool": "0x5fa00d2ba520f95f548ff0813f9f74facdf1b807",
                "feeFactor": "0.9985947383062085",
                "balAndRatioFactor": "1",
                "wrapFactor": "1",
                "valueUSD": "71.751683556645324588",
                "factorUSD": "71.65085366427812146"
            }
        ],
        "0x7E82a7Bb5E6787bEB07C363A0fbb42304AC04525": [
            {
                "pool": "0x5fa00d2ba520f95f548ff0813f9f74facdf1b807",
                "feeFactor": "0.9985947383062085",
                "balAndRatioFactor": "1",
                "wrapFactor": "1",
                "valueUSD": "2582.718067331683800276",
                "factorUSD": "2579.088672565799368956"
            }
        ],
        "0x810658c23C13624B8e54A4652332D1b1439c4127": [
            {
                "pool": "0x5fa00d2ba520f95f548ff0813f9f74facdf1b807",
                "feeFactor": "0.9985947383062085",
                "balAndRatioFactor": "1",
                "wrapFactor": "1",
                "valueUSD": "4399.478140882858525391",
                "factorUSD": "4393.295722778802800156"
            }
        ],
        "0x85b8927cEA8649e20f64a8C0192D0CE460605B94": [
            {
                "pool": "0x5fa00d2ba520f95f548ff0813f9f74facdf1b807",
                "feeFactor": "0.9985947383062085",
                "balAndRatioFactor": "1",
                "wrapFactor": "1",
                "valueUSD": "11.420136382815295062",
                "factorUSD": "11.404088102618650107"
            }
        ],
        "0x8b437D4bD3C5d73c5A8fA26ade78FA5770FD6528": [
            {
                "pool": "0x5fa00d2ba520f95f548ff0813f9f74facdf1b807",
                "feeFactor": "0.9985947383062085",
                "balAndRatioFactor": "1",
                "wrapFactor": "1",
                "valueUSD": "33.55661939531490326",
                "factorUSD": "33.509463563505526338"
            }
        ],
        "0x9080772c1bE19235Fd010C11b2739dd199a0705E": [
            {
                "pool": "0x5fa00d2ba520f95f548ff0813f9f74facdf1b807",
                "feeFactor": "0.9985947383062085",
                "balAndRatioFactor": "1",
                "wrapFactor": "1",
                "valueUSD": "28.131432522202508083",
                "factorUSD": "28.091900497687576498"
            }
        ],
        "0x9457dA5a017B96f81dd5887159f8aF268685CCB5": [
            {
                "pool": "0x5fa00d2ba520f95f548ff0813f9f74facdf1b807",
                "feeFactor": "0.9985947383062085",
                "balAndRatioFactor": "1",
                "wrapFactor": "1",
                "valueUSD": "91.236026239751933575",
                "factorUSD": "91.107815746983454034"
            }
        ],
        "0x9c1D152cC101a68226c7DE4D502f52ba0D76Dc75": [
            {
                "pool": "0x5fa00d2ba520f95f548ff0813f9f74facdf1b807",
                "feeFactor": "0.9985947383062085",
                "balAndRatioFactor": "1",
                "wrapFactor": "1",
                "valueUSD": "33.756728130347574253",
                "factorUSD": "33.709291093398262845"
            }
        ],
        "0x9e145a59854686012308F3700b611080C8A8fd55": [
            {
                "pool": "0x5fa00d2ba520f95f548ff0813f9f74facdf1b807",
                "feeFactor": "0.9985947383062085",
                "balAndRatioFactor": "1",
                "wrapFactor": "1",
                "valueUSD": "20.928262210504324352",
                "factorUSD": "20.898852525302278403"
            }
        ],
        "0xA537636fe55DCDa148c131A041c24d16622Fc792": [
            {
                "pool": "0x5fa00d2ba520f95f548ff0813f9f74facdf1b807",
                "feeFactor": "0.9985947383062085",
                "balAndRatioFactor": "1",
                "wrapFactor": "1",
                "valueUSD": "208.385741282791262341",
                "factorUSD": "208.092904783034209786"
            }
        ],
        "0xa805E1A75a9BDa9A3D60398727e26c92e152B27a": [
            {
                "pool": "0x5fa00d2ba520f95f548ff0813f9f74facdf1b807",
                "feeFactor": "0.9985947383062085",
                "balAndRatioFactor": "1",
                "wrapFactor": "1",
                "valueUSD": "242.808186936080983251",
                "factorUSD": "242.466977892040742926"
            }
        ],
        "0xa86059823717Fe4Cc998699044b66BE2E4DC67C5": [
            {
                "pool": "0x5fa00d2ba520f95f548ff0813f9f74facdf1b807",
                "feeFactor": "0.9985947383062085",
                "balAndRatioFactor": "1",
                "wrapFactor": "1",
                "valueUSD": "130905.208308216076449689",
                "factorUSD": "130721.252233462743587912"
            }
        ],
        "0xAc31b377337037352F0673e66a0b473499355513": [
            {
                "pool": "0x5fa00d2ba520f95f548ff0813f9f74facdf1b807",
                "feeFactor": "0.9985947383062085",
                "balAndRatioFactor": "1",
                "wrapFactor": "1",
                "valueUSD": "75.790031355490140749",
                "factorUSD": "75.683526527655013779"
            }
        ],
        "0xaF96Ce1e1952B2308eb36515867E041f32490EF4": [
            {
                "pool": "0x5fa00d2ba520f95f548ff0813f9f74facdf1b807",
                "feeFactor": "0.9985947383062085",
                "balAndRatioFactor": "1",
                "wrapFactor": "1",
                "valueUSD": "1720.751820519253168347",
                "factorUSD": "1718.333713901355475435"
            }
        ],
        "0xb2dA66eB8797Df7eAd05D37edA66dc56F1a128B4": [
            {
                "pool": "0x5fa00d2ba520f95f548ff0813f9f74facdf1b807",
                "feeFactor": "0.9985947383062085",
                "balAndRatioFactor": "1",
                "wrapFactor": "1",
                "valueUSD": "212.946209383097261649",
                "factorUSD": "212.646964232213090981"
            }
        ],
        "0xB85246cE9eB29b8C9103a35732Dd105f19cDf7A0": [
            {
                "pool": "0x5fa00d2ba520f95f548ff0813f9f74facdf1b807",
                "feeFactor": "0.9985947383062085",
                "balAndRatioFactor": "1",
                "wrapFactor": "1",
                "valueUSD": "32.551301799777868743",
                "factorUSD": "32.505558702275594593"
            }
        ],
        "0xB88f5E9ea2B66F20D38158E4a4EFb04F4E442d17": [
            {
                "pool": "0x5fa00d2ba520f95f548ff0813f9f74facdf1b807",
                "feeFactor": "0.9985947383062085",
                "balAndRatioFactor": "1",
                "wrapFactor": "1",
                "valueUSD": "19.055526485511531834",
                "factorUSD": "19.02874848408641311"
            }
        ],
        "0xb89953b858d014dE8637DA08ABBb93DC9cDac4Dc": [
            {
                "pool": "0x5fa00d2ba520f95f548ff0813f9f74facdf1b807",
                "feeFactor": "0.9985947383062085",
                "balAndRatioFactor": "1",
                "wrapFactor": "1",
                "valueUSD": "1822.66461187049515613",
                "factorUSD": "1820.103291110804197169"
            }
        ],
        "0xbb5b6bc87B901c83850E04b2b838281bC13E3d0b": [
            {
                "pool": "0x5fa00d2ba520f95f548ff0813f9f74facdf1b807",
                "feeFactor": "0.9985947383062085",
                "balAndRatioFactor": "1",
                "wrapFactor": "1",
                "valueUSD": "198.578037803402261315",
                "factorUSD": "198.298983693648859736"
            }
        ],
        "0xbDe8Fc6c5aB51A210fd249c1f516AEc340E4A0F0": [
            {
                "pool": "0x5fa00d2ba520f95f548ff0813f9f74facdf1b807",
                "feeFactor": "0.9985947383062085",
                "balAndRatioFactor": "1",
                "wrapFactor": "1",
                "valueUSD": "9.635421373998521421",
                "factorUSD": "9.621881085438101436"
            }
        ],
        "0xbF45974D2F19fF56beaa57e383bC2a0CC0891Ded": [
            {
                "pool": "0x5fa00d2ba520f95f548ff0813f9f74facdf1b807",
                "feeFactor": "0.9985947383062085",
                "balAndRatioFactor": "1",
                "wrapFactor": "1",
                "valueUSD": "14.298601478327314811",
                "factorUSD": "14.278508201395030923"
            }
        ],
        "0xbf82887e80F4fF9B5002a7DFDdC1Fc2d803582f3": [
            {
                "pool": "0x5fa00d2ba520f95f548ff0813f9f74facdf1b807",
                "feeFactor": "0.9985947383062085",
                "balAndRatioFactor": "1",
                "wrapFactor": "1",
                "valueUSD": "6.235636527904193647",
                "factorUSD": "6.226873826755122852"
            }
        ],
        "0xC002440acA0438738bd87b1a93Dc4Eb86903D6Ca": [
            {
                "pool": "0x5fa00d2ba520f95f548ff0813f9f74facdf1b807",
                "feeFactor": "0.9985947383062085",
                "balAndRatioFactor": "1",
                "wrapFactor": "1",
                "valueUSD": "19.042189460821800723",
                "factorUSD": "19.01543020140658763"
            }
        ],
        "0xC104101E06a9B6669E401574665C656B9f4a9117": [
            {
                "pool": "0x5fa00d2ba520f95f548ff0813f9f74facdf1b807",
                "feeFactor": "0.9985947383062085",
                "balAndRatioFactor": "1",
                "wrapFactor": "1",
                "valueUSD": "9.47842667672289497",
                "factorUSD": "9.465107006796684817"
            }
        ],
        "0xc1d1742bBB0c0Dd61C9E4cfC137B59B1a8f55B90": [
            {
                "pool": "0x5fa00d2ba520f95f548ff0813f9f74facdf1b807",
                "feeFactor": "0.9985947383062085",
                "balAndRatioFactor": "1",
                "wrapFactor": "1",
                "valueUSD": "0.057120849688159588",
                "factorUSD": "0.057040579946175995"
            }
        ],
        "0xC50632240A8ec1679912600D38992A521C9B87f8": [
            {
                "pool": "0x5fa00d2ba520f95f548ff0813f9f74facdf1b807",
                "feeFactor": "0.9985947383062085",
                "balAndRatioFactor": "1",
                "wrapFactor": "1",
                "valueUSD": "294.558896648139318699",
                "factorUSD": "294.144964314114199048"
            }
        ],
        "0xC5d5358634cE55625c313e08a993d0340F9336C2": [
            {
                "pool": "0x5fa00d2ba520f95f548ff0813f9f74facdf1b807",
                "feeFactor": "0.9985947383062085",
                "balAndRatioFactor": "1",
                "wrapFactor": "1",
                "valueUSD": "26.604691356463417267",
                "factorUSD": "26.567304802825033406"
            }
        ],
        "0xC71819B6A46987AF42Cf76D466535605F2913e50": [
            {
                "pool": "0x5fa00d2ba520f95f548ff0813f9f74facdf1b807",
                "feeFactor": "0.9985947383062085",
                "balAndRatioFactor": "1",
                "wrapFactor": "1",
                "valueUSD": "63.767618216889089185",
                "factorUSD": "63.678008025704573913"
            }
        ],
        "0xc988d25d20848CFbc22D771577e1395e8F228dFB": [
            {
                "pool": "0x5fa00d2ba520f95f548ff0813f9f74facdf1b807",
                "feeFactor": "0.9985947383062085",
                "balAndRatioFactor": "1",
                "wrapFactor": "1",
                "valueUSD": "19.293063716083867521",
                "factorUSD": "19.265951912687776174"
            }
        ],
        "0xcAA43Da67191804c3852A027fEFc363b801Ff824": [
            {
                "pool": "0x5fa00d2ba520f95f548ff0813f9f74facdf1b807",
                "feeFactor": "0.9985947383062085",
                "balAndRatioFactor": "1",
                "wrapFactor": "1",
                "valueUSD": "22.750564499901977869",
                "factorUSD": "22.718594003098132846"
            }
        ],
        "0xcb1B609958e6f02314869a67bebd25ffB719e84c": [
            {
                "pool": "0x5fa00d2ba520f95f548ff0813f9f74facdf1b807",
                "feeFactor": "0.9985947383062085",
                "balAndRatioFactor": "1",
                "wrapFactor": "1",
                "valueUSD": "11.433468400945808617",
                "factorUSD": "11.417401385774783917"
            }
        ],
        "0xcc112a107ABe98901B9EfD9ac4880A143dF48083": [
            {
                "pool": "0x5fa00d2ba520f95f548ff0813f9f74facdf1b807",
                "feeFactor": "0.9985947383062085",
                "balAndRatioFactor": "1",
                "wrapFactor": "1",
                "valueUSD": "5.59713515047914272",
                "factorUSD": "5.589269710857200457"
            }
        ],
        "0xCC2604E90c441A971C513F842918339b6cd5bD8B": [
            {
                "pool": "0x5fa00d2ba520f95f548ff0813f9f74facdf1b807",
                "feeFactor": "0.9985947383062085",
                "balAndRatioFactor": "1",
                "wrapFactor": "1",
                "valueUSD": "72.548502621458767237",
                "factorUSD": "72.446552989782899011"
            }
        ],
        "0xcf12e648c37675c64EE2280B0EFB4B05C21b346C": [
            {
                "pool": "0x5fa00d2ba520f95f548ff0813f9f74facdf1b807",
                "feeFactor": "0.9985947383062085",
                "balAndRatioFactor": "1",
                "wrapFactor": "1",
                "valueUSD": "296.220551305244079504",
                "factorUSD": "295.804283911581020282"
            }
        ],
        "0xd874387eBb001a6B0BEa98072f8dE05f8965E51E": [
            {
                "pool": "0x5fa00d2ba520f95f548ff0813f9f74facdf1b807",
                "feeFactor": "0.9985947383062085",
                "balAndRatioFactor": "1",
                "wrapFactor": "1",
                "valueUSD": "9.076182681241302312",
                "factorUSD": "9.063428269393500082"
            }
        ],
        "0xDAe6eaF250e4F4d89fb90b404964CBdeAFAD7aD2": [
            {
                "pool": "0x5fa00d2ba520f95f548ff0813f9f74facdf1b807",
                "feeFactor": "0.9985947383062085",
                "balAndRatioFactor": "1",
                "wrapFactor": "1",
                "valueUSD": "19.042189460821436556",
                "factorUSD": "19.015430201406223974"
            }
        ],
        "0xDaf7d144385ddC1f460AD3ED077b3d7Fa47D7378": [
            {
                "pool": "0x5fa00d2ba520f95f548ff0813f9f74facdf1b807",
                "feeFactor": "0.9985947383062085",
                "balAndRatioFactor": "1",
                "wrapFactor": "1",
                "valueUSD": "22.704200322566930367",
                "factorUSD": "22.672294979565458442"
            }
        ],
        "0xdc4489E2497a2824100FB9c98F24303f1041A050": [
            {
                "pool": "0x5fa00d2ba520f95f548ff0813f9f74facdf1b807",
                "feeFactor": "0.9985947383062085",
                "balAndRatioFactor": "1",
                "wrapFactor": "1",
                "valueUSD": "228.553124923309436799",
                "factorUSD": "228.231947971858366686"
            }
        ],
        "0xe113E373D697f64b8a64CC10151445619895b577": [
            {
                "pool": "0x5fa00d2ba520f95f548ff0813f9f74facdf1b807",
                "feeFactor": "0.9985947383062085",
                "balAndRatioFactor": "1",
                "wrapFactor": "1",
                "valueUSD": "2.251746087630533765",
                "factorUSD": "2.248581795109441698"
            }
        ],
        "0xe43192C078E391D6243e7e45828C0669162bB9e7": [
            {
                "pool": "0x5fa00d2ba520f95f548ff0813f9f74facdf1b807",
                "feeFactor": "0.9985947383062085",
                "balAndRatioFactor": "1",
                "wrapFactor": "1",
                "valueUSD": "173137.416772781771412944",
                "factorUSD": "172894.113393228967239153"
            }
        ],
        "0xE65111375919D925A61D3c4B28E637Ba943Ffce3": [
            {
                "pool": "0x5fa00d2ba520f95f548ff0813f9f74facdf1b807",
                "feeFactor": "0.9985947383062085",
                "balAndRatioFactor": "1",
                "wrapFactor": "1",
                "valueUSD": "6.467392714431587676",
                "factorUSD": "6.458304335191290736"
            }
        ],
        "0xE76B9F02e9Ebe741C1105A0a824c991895E6Aeaf": [
            {
                "pool": "0x5fa00d2ba520f95f548ff0813f9f74facdf1b807",
                "feeFactor": "0.9985947383062085",
                "balAndRatioFactor": "1",
                "wrapFactor": "1",
                "valueUSD": "44.400782322187249503",
                "factorUSD": "44.338387603615504958"
            }
        ],
        "0xe7771e755344b12bd856526Ed447A145838B41f5": [
            {
                "pool": "0x5fa00d2ba520f95f548ff0813f9f74facdf1b807",
                "feeFactor": "0.9985947383062085",
                "balAndRatioFactor": "1",
                "wrapFactor": "1",
                "valueUSD": "172.132407684761605861",
                "factorUSD": "171.890516605982108756"
            }
        ],
        "0xeAe9DcdF5D4f226B4D4bAD8950D585Aa95761B7B": [
            {
                "pool": "0x5fa00d2ba520f95f548ff0813f9f74facdf1b807",
                "feeFactor": "0.9985947383062085",
                "balAndRatioFactor": "1",
                "wrapFactor": "1",
                "valueUSD": "0.94777027692581168",
                "factorUSD": "0.946438411661133675"
            }
        ],
        "0xeC42145Bc158b4A7a82a0cae946109eC4F356EAA": [
            {
                "pool": "0x5fa00d2ba520f95f548ff0813f9f74facdf1b807",
                "feeFactor": "0.9985947383062085",
                "balAndRatioFactor": "1",
                "wrapFactor": "1",
                "valueUSD": "5008.907832511457232176",
                "factorUSD": "5001.869006206696670795"
            }
        ],
        "0xee79dc76EB20a2127040ffF07df58840C477CeC6": [
            {
                "pool": "0x5fa00d2ba520f95f548ff0813f9f74facdf1b807",
                "feeFactor": "0.9985947383062085",
                "balAndRatioFactor": "1",
                "wrapFactor": "1",
                "valueUSD": "0.947474087974091813",
                "factorUSD": "0.946142638932401784"
            }
        ],
        "0xf244eA81F715F343040569398A4E7978De656bf6": [
            {
                "pool": "0x5fa00d2ba520f95f548ff0813f9f74facdf1b807",
                "feeFactor": "0.9985947383062085",
                "balAndRatioFactor": "1",
                "wrapFactor": "1",
                "valueUSD": "220.988556448812420369",
                "factorUSD": "220.678009695668623716"
            }
        ],
        "0xF3fB95bdbcdB3E70b9889EC8Cb3A01d22f0508eC": [
            {
                "pool": "0x5fa00d2ba520f95f548ff0813f9f74facdf1b807",
                "feeFactor": "0.9985947383062085",
                "balAndRatioFactor": "1",
                "wrapFactor": "1",
                "valueUSD": "89.881190202689550592",
                "factorUSD": "89.754883609105323099"
            }
        ],
        "0xf559C930e0Ab373f5e596b643d14Cfaa5a69389C": [
            {
                "pool": "0x5fa00d2ba520f95f548ff0813f9f74facdf1b807",
                "feeFactor": "0.9985947383062085",
                "balAndRatioFactor": "1",
                "wrapFactor": "1",
                "valueUSD": "13.336034576672568576",
                "factorUSD": "13.317293958134891673"
            }
        ],
        "0xf598FdA39E2DD32517D83d7195EF174e139ac088": [
            {
                "pool": "0x5fa00d2ba520f95f548ff0813f9f74facdf1b807",
                "feeFactor": "0.9985947383062085",
                "balAndRatioFactor": "1",
                "wrapFactor": "1",
                "valueUSD": "33.659266977233039675",
                "factorUSD": "33.611966898708832872"
            }
        ],
        "0xf728B6824110deF33c4f2696D1aB0098e8c6081f": [
            {
                "pool": "0x5fa00d2ba520f95f548ff0813f9f74facdf1b807",
                "feeFactor": "0.9985947383062085",
                "balAndRatioFactor": "1",
                "wrapFactor": "1",
                "valueUSD": "29.695662215054362135",
                "factorUSD": "29.653932038471774596"
            }
        ],
        "0xf770e0aABb915b0b485cf39882cE00a0F0660A46": [
            {
                "pool": "0x5fa00d2ba520f95f548ff0813f9f74facdf1b807",
                "feeFactor": "0.9985947383062085",
                "balAndRatioFactor": "1",
                "wrapFactor": "1",
                "valueUSD": "21.098707983532634988",
                "factorUSD": "21.069058777414883674"
            }
        ],
        "0xF93b99Bcc04c3D62EE3a950822446e344db2d112": [
            {
                "pool": "0x5fa00d2ba520f95f548ff0813f9f74facdf1b807",
                "feeFactor": "0.9985947383062085",
                "balAndRatioFactor": "1",
                "wrapFactor": "1",
                "valueUSD": "0.900110972224385855",
                "factorUSD": "0.898846080754957501"
            }
        ],
        "0xFf2357963D6eA5139175c26aD88CEcBD2B273dce": [
            {
                "pool": "0x5fa00d2ba520f95f548ff0813f9f74facdf1b807",
                "feeFactor": "0.9985947383062085",
                "balAndRatioFactor": "1",
                "wrapFactor": "1",
                "valueUSD": "2.230446797545740871",
                "factorUSD": "2.227312436101109916"
            }
        ]
    },
    {
        "0x03c6592bC87E7fDF583B5337A0e344B832bcBdec": "0.000177250597990768",
        "0x05695FacB3337A65286B47F1d43f6737F3005c20": "0.000027718258809964",
        "0x05c1Ff33107b857c4FAa6F1425BA78e98Ab74E9d": "0.000025648694625386",
        "0x0b64Ebfb2694cF6dfEb6F5980Ed137849C5B246A": "0.000062624417688648",
        "0x0fDA4Ac09a12C10FAe30E429F4D6b47C9A83c87e": "0.001778664232136004",
        "0x126BbF0dc21fb51d93367560dAc2493bc5E1492a": "0.000179607210650047",
        "0x14602524171f1FF792cE532BeD1fB3ac6e2Fa9Df": "0.000009918513146258",
        "0x16894007836e9F29A4349EA4422aE26db64DEF0B": "0.000033248375048693",
        "0x169833EBB85FBD3cb67eeC73Ed02f738c0017951": "0.000111180234625979",
        "0x1Bec4f239F1Ec11FD8DC7B31A8fea7A5bA5a9Aa4": "0.003277665466286875",
        "0x1dCBB7863137b0928AC30D9e834fFe166c0772A0": "0.000031425912874488",
        "0x1DF6DB610036713fE15AAa1EAdF9DfCbB9F2d7B8": "0.036667163480417054",
        "0x1e81eED69C5357713084C96D88c1C4c413De6e7e": "0.001033985774034135",
        "0x2186473547fA23D3AB86dA9EC53fA56cC55C7e0E": "0.000008821916756465",
        "0x25aD2667B19e866109c1a93102b816730a6Aec3f": "0.000041370991669376",
        "0x266cA9F02E8395D7cC746CB6Ec986C2E06c75a28": "0.001096424704748795",
        "0x28440FecB243B268E1484e72ce98Bd866848E144": "0.000179609354302783",
        "0x28BAb5CECBd39870Db7daa7Ec29Ba219D0865804": "0.000185643013736297",
        "0x2949d0157Ef65a9226a4A0E0cFd0Ac52433520d9": "0.001641670446752085",
        "0x29f46A92078f6011A47dF128aF735208782579bF": "0.000008864972934836",
        "0x2C982f6926B66b9CCB9999D527De55c74697bba5": "0.000059586118514559",
        "0x32BcCA9f63aBE93195689f6Af28B5677c39C8356": "0.000020598113472423",
        "0x34E467c9A3B3C5767539AB3Df5A49314d8DEB466": "0.000127633552612774",
        "0x366b862656D5F06d506D6FC2C1e31425C2cCFC3f": "0.000097221352275723",
        "0x38376A546C30bd84146f7e4C08cC596DF8aa10C2": "0.000203011779197252",
        "0x3b43e78D75903CB755AF4fC94fA7348b49d5F460": "0.000414839334936201",
        "0x43d1eb966d0ADfe9E5C0d3Cff1223bed0823225C": "0.000006614917938985",
        "0x44909bDd05ddA8A13c681414Cf684Bf148d5f411": "0.000020755332236543",
        "0x4598B7560f51D6325Ab0212d063012F720e97504": "0.000175737402458431",
        "0x49cADC6F25b9FA00D7dF4f3cE4caD7180f0BD2Ce": "0.000179609354302783",
        "0x4C89d3625f581dfa803fF7C102b99B72efDc500c": "0.000269626565700565",
        "0x4E0985E556069B3D69f4E76DB3e2B8D2B5047956": "0.141386785468828207",
        "0x507CC427C8Fba38b81E891549189E6718862Af45": "0.000010646447159925",
        "0x51fF13A729c61ec0a10555F92028c4d07b16970b": "0.004323302563955705",
        "0x52b4Fab7FD9565011703e0dB38FF70882838E085": "0.004992513115652265",
        "0x56f386B8889Fc0FbAF0f5300937B3fe0e9064a8f": "0.000357731947909982",
        "0x57A07c76A8c5D497Db4BCaB8884869b0998ac726": "0.000179609354302783",
        "0x611dCd191690a60A4ed50021505882762c316Bc0": "0.184417953541902815",
        "0x646f535ABEBc5d9755c0101C3F813D76C0a1E0C8": "0.000020590856126104",
        "0x69acB25746533Cd28147eAfF75d001598374454f": "0.000000173643410882",
        "0x6C924AB13f2de31Ff1f9B0394933Ae0f5D4a7a21": "0.000177250597990768",
        "0x719450B5feD41e3ea88aCA1745Db525a841366Ac": "0.000177250597990768",
        "0x72F42Fa01716D6525B1385fb9aBD2Fd125785F30": "0.000032291252525339",
        "0x73692E42db099B426885b9fB5D4B46EA7fFD4DAa": "0.001639708491083364",
        "0x742F6A3589168856deF641FA29BBDb2B51B12488": "0.000348757143704687",
        "0x7560E255F7D5ABd4Af80D48f9834bad510A27835": "0.000312396352952086",
        "0x7C684BA5387688b2dF88A51F759aaD4A4b07Ccc5": "0.000667974446329294",
        "0x7E82a7Bb5E6787bEB07C363A0fbb42304AC04525": "0.024043891174882067",
        "0x810658c23C13624B8e54A4652332D1b1439c4127": "0.04095707347374015",
        "0x85b8927cEA8649e20f64a8C0192D0CE460605B94": "0.000106316101576816",
        "0x8b437D4bD3C5d73c5A8fA26ade78FA5770FD6528": "0.000312396352952086",
        "0x9080772c1bE19235Fd010C11b2739dd199a0705E": "0.000261890413325746",
        "0x9457dA5a017B96f81dd5887159f8aF268685CCB5": "0.000849364517902507",
        "0x9c1D152cC101a68226c7DE4D502f52ba0D76Dc75": "0.000314259271212165",
        "0x9e145a59854686012308F3700b611080C8A8fd55": "0.000194832283644737",
        "0xA537636fe55DCDa148c131A041c24d16622Fc792": "0.001939973297579869",
        "0xa805E1A75a9BDa9A3D60398727e26c92e152B27a": "0.002260430086003574",
        "0xa86059823717Fe4Cc998699044b66BE2E4DC67C5": "1.21866595607154356",
        "0xAc31b377337037352F0673e66a0b473499355513": "0.000705569566071521",
        "0xaF96Ce1e1952B2308eb36515867E041f32490EF4": "0.01601939059275251",
        "0xb2dA66eB8797Df7eAd05D37edA66dc56F1a128B4": "0.001982429111900928",
        "0xB85246cE9eB29b8C9103a35732Dd105f19cDf7A0": "0.000303037318697039",
        "0xB88f5E9ea2B66F20D38158E4a4EFb04F4E442d17": "0.000177397994342862",
        "0xb89953b858d014dE8637DA08ABBb93DC9cDac4Dc": "0.016968150775124764",
        "0xbb5b6bc87B901c83850E04b2b838281bC13E3d0b": "0.001848668188394037",
        "0xbDe8Fc6c5aB51A210fd249c1f516AEc340E4A0F0": "0.000089701243767538",
        "0xbF45974D2F19fF56beaa57e383bC2a0CC0891Ded": "0.000133113258565263",
        "0xbf82887e80F4fF9B5002a7DFDdC1Fc2d803582f3": "0.000058050844952634",
        "0xC002440acA0438738bd87b1a93Dc4Eb86903D6Ca": "0.000177273832912199",
        "0xC104101E06a9B6669E401574665C656B9f4a9117": "0.0000882396969328",
        "0xc1d1742bBB0c0Dd61C9E4cfC137B59B1a8f55B90": "0.000000531768260377",
        "0xC50632240A8ec1679912600D38992A521C9B87f8": "0.002742204867493825",
        "0xC5d5358634cE55625c313e08a993d0340F9336C2": "0.000247677170732384",
        "0xC71819B6A46987AF42Cf76D466535605F2913e50": "0.000593646551004437",
        "0xc988d25d20848CFbc22D771577e1395e8F228dFB": "0.000179609354302783",
        "0xcAA43Da67191804c3852A027fEFc363b801Ff824": "0.000211797061367953",
        "0xcb1B609958e6f02314869a67bebd25ffB719e84c": "0.000106440216398765",
        "0xcc112a107ABe98901B9EfD9ac4880A143dF48083": "0.000052106697262646",
        "0xCC2604E90c441A971C513F842918339b6cd5bD8B": "0.000675392457270085",
        "0xcf12e648c37675c64EE2280B0EFB4B05C21b346C": "0.00275767409127439",
        "0xd874387eBb001a6B0BEa98072f8dE05f8965E51E": "0.000084494994413604",
        "0xDAe6eaF250e4F4d89fb90b404964CBdeAFAD7aD2": "0.000177273832912196",
        "0xDaf7d144385ddC1f460AD3ED077b3d7Fa47D7378": "0.0002113654326709",
        "0xdc4489E2497a2824100FB9c98F24303f1041A050": "0.002127722159396478",
        "0xe113E373D697f64b8a64CC10151445619895b577": "0.000020962697620488",
        "0xe43192C078E391D6243e7e45828C0669162bB9e7": "1.611827965212568993",
        "0xE65111375919D925A61D3c4B28E637Ba943Ffce3": "0.000060208386109934",
        "0xE76B9F02e9Ebe741C1105A0a824c991895E6Aeaf": "0.000413350412396053",
        "0xe7771e755344b12bd856526Ed447A145838B41f5": "0.001602471803017483",
        "0xeAe9DcdF5D4f226B4D4bAD8950D585Aa95761B7B": "0.000008823295769455",
        "0xeC42145Bc158b4A7a82a0cae946109eC4F356EAA": "0.046630577434394542",
        "0xee79dc76EB20a2127040ffF07df58840C477CeC6": "0.000008820538389541",
        "0xf244eA81F715F343040569398A4E7978De656bf6": "0.002057299582698566",
        "0xF3fB95bdbcdB3E70b9889EC8Cb3A01d22f0508eC": "0.000836751631251433",
        "0xf559C930e0Ab373f5e596b643d14Cfaa5a69389C": "0.000124152213174877",
        "0xf598FdA39E2DD32517D83d7195EF174e139ac088": "0.000313351953689241",
        "0xf728B6824110deF33c4f2696D1aB0098e8c6081f": "0.000276452656484677",
        "0xf770e0aABb915b0b485cf39882cE00a0F0660A46": "0.000196419053671922",
        "0xF93b99Bcc04c3D62EE3a950822446e344db2d112": "0.000008379610045408",
        "0xFf2357963D6eA5139175c26aD88CEcBD2B273dce": "0.000020764411241739"
    },
    {
        "0x765DE816845861e75A25fCA122bb6898B8B1282a": "181828.0100901762450493435",
        "0xD8763CBa276a3738E6DE85b4b3bF5FDed6D6cA73": "181828.0100901762450493435"
    }
]