[
    {
        "0x007De57773B6EB4ebbf6A740dFdE1EfDd5629630": [
            {
                "pool": "0xcd65f38b298310fa2c8b1844ea187016f913b0c8",
                "feeFactor": "0.9961013694701175",
                "balAndRatioFactor": "0.96",
                "wrapFactor": "1",
                "valueUSD": "0.438269601960712411",
                "factorUSD": "0.419098512681781369"
            }
        ],
        "0x02FF537c4e2995d7ce0Be764fEa5B9fa5d782Cf5": [
            {
                "pool": "0xcd65f38b298310fa2c8b1844ea187016f913b0c8",
                "feeFactor": "0.9961013694701175",
                "balAndRatioFactor": "0.96",
                "wrapFactor": "1",
                "valueUSD": "0.629686604130519678",
                "factorUSD": "0.602142421162942462"
            }
        ],
        "0x0dC437c879FaDa4Ac7E5554b0F8F1EE78343C26B": [
            {
                "pool": "0xcd65f38b298310fa2c8b1844ea187016f913b0c8",
                "feeFactor": "0.9961013694701175",
                "balAndRatioFactor": "0.96",
                "wrapFactor": "1",
                "valueUSD": "88.646467297055833038",
                "factorUSD": "84.768832774353888526"
            }
        ],
        "0x12db4993126eBcd26E8dFeF76Fe3aE539b47f25b": [
            {
                "pool": "0xcd65f38b298310fa2c8b1844ea187016f913b0c8",
                "feeFactor": "0.9961013694701175",
                "balAndRatioFactor": "0.96",
                "wrapFactor": "1",
                "valueUSD": "2391.68652821488172697",
                "factorUSD": "2287.067737054151525602"
            }
        ],
        "0x15eCd31318fa645B6496F1f21b22Ebfe3AD0c865": [
            {
                "pool": "0xcd65f38b298310fa2c8b1844ea187016f913b0c8",
                "feeFactor": "0.9961013694701175",
                "balAndRatioFactor": "0.96",
                "wrapFactor": "1",
                "valueUSD": "99.776714257840448065",
                "factorUSD": "95.412212844924930016"
            }
        ],
        "0x169833EBB85FBD3cb67eeC73Ed02f738c0017951": [
            {
                "pool": "0xcd65f38b298310fa2c8b1844ea187016f913b0c8",
                "feeFactor": "0.9961013694701175",
                "balAndRatioFactor": "0.96",
                "wrapFactor": "1",
                "valueUSD": "4913.628511965882328942",
                "factorUSD": "4698.693206243165780281"
            }
        ],
        "0x18fEe6e511646B8ea2e4964277574F637Bc03f3b": [
            {
                "pool": "0xcd65f38b298310fa2c8b1844ea187016f913b0c8",
                "feeFactor": "0.9961013694701175",
                "balAndRatioFactor": "0.96",
                "wrapFactor": "1",
                "valueUSD": "1891.752498973723513901",
                "factorUSD": "1809.002164729193320954"
            }
        ],
        "0x1c85d6Ae1336D0e4E3F165bbfA9641bfA04CeDb1": [
            {
                "pool": "0xcd65f38b298310fa2c8b1844ea187016f913b0c8",
                "feeFactor": "0.9961013694701175",
                "balAndRatioFactor": "0.96",
                "wrapFactor": "1",
                "valueUSD": "3.088989337211348984",
                "factorUSD": "2.953868648711822698"
            }
        ],
        "0x25a9b8B7Ff067DF3087fa015F91654360c26006C": [
            {
                "pool": "0xcd65f38b298310fa2c8b1844ea187016f913b0c8",
                "feeFactor": "0.9961013694701175",
                "balAndRatioFactor": "0.96",
                "wrapFactor": "1",
                "valueUSD": "79.776669721970851778",
                "factorUSD": "76.287023963347606428"
            }
        ],
        "0x26b350F462Ae30EC1c48c36ba944AB66F06dAFee": [
            {
                "pool": "0xcd65f38b298310fa2c8b1844ea187016f913b0c8",
                "feeFactor": "0.9961013694701175",
                "balAndRatioFactor": "0.96",
                "wrapFactor": "1",
                "valueUSD": "45.137901759830749364",
                "factorUSD": "43.163448727656034733"
            }
        ],
        "0x280A8675cF1d930c638F4f9Eb9dbe75823801D5a": [
            {
                "pool": "0xcd65f38b298310fa2c8b1844ea187016f913b0c8",
                "feeFactor": "0.9961013694701175",
                "balAndRatioFactor": "0.96",
                "wrapFactor": "1",
                "valueUSD": "487.385055723273861726",
                "factorUSD": "466.065524606613717851"
            }
        ],
        "0x2b1DEE0c00322E99775f76B60b5bBB7b04d1dFc3": [
            {
                "pool": "0xcd65f38b298310fa2c8b1844ea187016f913b0c8",
                "feeFactor": "0.9961013694701175",
                "balAndRatioFactor": "0.96",
                "wrapFactor": "1",
                "valueUSD": "0.080465492942649273",
                "factorUSD": "0.076945716206650575"
            }
        ],
        "0x2E78A0D97479cCb3238a4Cd5f373654bA09FEf2e": [
            {
                "pool": "0xcd65f38b298310fa2c8b1844ea187016f913b0c8",
                "feeFactor": "0.9961013694701175",
                "balAndRatioFactor": "0.96",
                "wrapFactor": "1",
                "valueUSD": "1.176682755241165659",
                "factorUSD": "1.125211491770492346"
            }
        ],
        "0x343EF442adD9bd565D51b606f444F9221AD0Aeb6": [
            {
                "pool": "0xcd65f38b298310fa2c8b1844ea187016f913b0c8",
                "feeFactor": "0.9961013694701175",
                "balAndRatioFactor": "0.96",
                "wrapFactor": "1",
                "valueUSD": "0.720562462432318287",
                "factorUSD": "0.689043125392888646"
            }
        ],
        "0x43a37B93b5930A978f325C426d38233Bc464cb5A": [
            {
                "pool": "0xcd65f38b298310fa2c8b1844ea187016f913b0c8",
                "feeFactor": "0.9961013694701175",
                "balAndRatioFactor": "0.96",
                "wrapFactor": "1",
                "valueUSD": "850.933529987058254596",
                "factorUSD": "813.71141236622402253"
            }
        ],
        "0x48Fda4c03bec8D10ceCc2d088B329a796E5360b6": [
            {
                "pool": "0xcd65f38b298310fa2c8b1844ea187016f913b0c8",
                "feeFactor": "0.9961013694701175",
                "balAndRatioFactor": "0.96",
                "wrapFactor": "1",
                "valueUSD": "58.113491018073844902",
                "factorUSD": "55.571450868281020573"
            }
        ],
        "0x4Cd0dCD8EB96E8F02273e9Ca02F2D937A3b48418": [
            {
                "pool": "0xcd65f38b298310fa2c8b1844ea187016f913b0c8",
                "feeFactor": "0.9961013694701175",
                "balAndRatioFactor": "0.96",
                "wrapFactor": "1",
                "valueUSD": "112.996496618567965145",
                "factorUSD": "108.053726425997809344"
            }
        ],
        "0x4dddafFEa0C4D6fee5afe772EA48c3B70026C09F": [
            {
                "pool": "0xcd65f38b298310fa2c8b1844ea187016f913b0c8",
                "feeFactor": "0.9961013694701175",
                "balAndRatioFactor": "0.96",
                "wrapFactor": "1",
                "valueUSD": "57.809149036981813647",
                "factorUSD": "55.280421622694120472"
            }
        ],
        "0x4ef416AA741053b5F3968900379DF2e3d0229065": [
            {
                "pool": "0xcd65f38b298310fa2c8b1844ea187016f913b0c8",
                "feeFactor": "0.9961013694701175",
                "balAndRatioFactor": "0.96",
                "wrapFactor": "1",
                "valueUSD": "0",
                "factorUSD": "0"
            }
        ],
        "0x4fFAD6ac852c0Af0AA301376F4C5Dea3a928b120": [
            {
                "pool": "0xcd65f38b298310fa2c8b1844ea187016f913b0c8",
                "feeFactor": "0.9961013694701175",
                "balAndRatioFactor": "0.96",
                "wrapFactor": "1",
                "valueUSD": "514.484870067261287421",
                "factorUSD": "491.979920299828254129"
            }
        ],
        "0x4FfD0A59a26cB2Aa76D403215e4cC2845C053994": [
            {
                "pool": "0xcd65f38b298310fa2c8b1844ea187016f913b0c8",
                "feeFactor": "0.9961013694701175",
                "balAndRatioFactor": "0.96",
                "wrapFactor": "1",
                "valueUSD": "30.264777743583918308",
                "factorUSD": "28.940915094808966698"
            }
        ],
        "0x50BBf827267C4E920B512F8aA6c1c9d1a465a128": [
            {
                "pool": "0xcd65f38b298310fa2c8b1844ea187016f913b0c8",
                "feeFactor": "0.9961013694701175",
                "balAndRatioFactor": "0.96",
                "wrapFactor": "1",
                "valueUSD": "1.444965734593497928",
                "factorUSD": "1.381759053183338518"
            }
        ],
        "0x543F39508598e746978452Ce608b50a58A7455F2": [
            {
                "pool": "0xcd65f38b298310fa2c8b1844ea187016f913b0c8",
                "feeFactor": "0.9961013694701175",
                "balAndRatioFactor": "0.96",
                "wrapFactor": "1",
                "valueUSD": "1.177860083403849613",
                "factorUSD": "1.126337320437850961"
            }
        ],
        "0x59b8C949D5eB9feE0ba981fc3FDAa9E5B64652CE": [
            {
                "pool": "0xcd65f38b298310fa2c8b1844ea187016f913b0c8",
                "feeFactor": "0.9961013694701175",
                "balAndRatioFactor": "0.96",
                "wrapFactor": "1",
                "valueUSD": "1.487870588442288147",
                "factorUSD": "1.42278713351200589"
            }
        ],
        "0x689cC0Ea1140546a8a7985315E9C8fef7e0461bc": [
            {
                "pool": "0xcd65f38b298310fa2c8b1844ea187016f913b0c8",
                "feeFactor": "0.9961013694701175",
                "balAndRatioFactor": "0.96",
                "wrapFactor": "1",
                "valueUSD": "66305.009786923890177987",
                "factorUSD": "63404.650609425053513858"
            }
        ],
        "0x6a1afc8a229d820015361Da64819e64E6A0258F9": [
            {
                "pool": "0xcd65f38b298310fa2c8b1844ea187016f913b0c8",
                "feeFactor": "0.9961013694701175",
                "balAndRatioFactor": "0.96",
                "wrapFactor": "1",
                "valueUSD": "0.97067238086478664",
                "factorUSD": "0.928212564370784111"
            }
        ],
        "0x6AFBC428dcdE09679592B330a9164247E9614BD3": [
            {
                "pool": "0xcd65f38b298310fa2c8b1844ea187016f913b0c8",
                "feeFactor": "0.9961013694701175",
                "balAndRatioFactor": "0.96",
                "wrapFactor": "1",
                "valueUSD": "269.235888758204111214",
                "factorUSD": "257.458788002449274971"
            }
        ],
        "0x6E0B6FF7536100a9e6b7041CA5a98108935932e5": [
            {
                "pool": "0xcd65f38b298310fa2c8b1844ea187016f913b0c8",
                "feeFactor": "0.9961013694701175",
                "balAndRatioFactor": "0.96",
                "wrapFactor": "1",
                "valueUSD": "1.894697967250358335",
                "factorUSD": "1.811818790313916584"
            }
        ],
        "0x6Ff1dd1443289CC30aA3A010b6EF7BB4058D8C54": [
            {
                "pool": "0xcd65f38b298310fa2c8b1844ea187016f913b0c8",
                "feeFactor": "0.9961013694701175",
                "balAndRatioFactor": "0.96",
                "wrapFactor": "1",
                "valueUSD": "0.048509822788839398",
                "factorUSD": "0.046387872876207013"
            }
        ],
        "0x751f556a157f8cb70d5f37086664b437F339D914": [
            {
                "pool": "0xcd65f38b298310fa2c8b1844ea187016f913b0c8",
                "feeFactor": "0.9961013694701175",
                "balAndRatioFactor": "0.96",
                "wrapFactor": "1",
                "valueUSD": "19.883736951896299317",
                "factorUSD": "19.013968903648784258"
            }
        ],
        "0x7Ad5583713ca971F2aE1E0a894486a9406179eca": [
            {
                "pool": "0xcd65f38b298310fa2c8b1844ea187016f913b0c8",
                "feeFactor": "0.9961013694701175",
                "balAndRatioFactor": "0.96",
                "wrapFactor": "1",
                "valueUSD": "2.429125715010413881",
                "factorUSD": "2.322869233283473559"
            }
        ],
        "0x7B72Cf70FD7Ce243b84AD2dC49EA44f970B95D42": [
            {
                "pool": "0xcd65f38b298310fa2c8b1844ea187016f913b0c8",
                "feeFactor": "0.9961013694701175",
                "balAndRatioFactor": "0.96",
                "wrapFactor": "1",
                "valueUSD": "5951.943986463005065923",
                "factorUSD": "5691.589973688220647433"
            }
        ],
        "0x7E8416AD4DE6e12A807BC3A987ae53B0299C96Fb": [
            {
                "pool": "0xcd65f38b298310fa2c8b1844ea187016f913b0c8",
                "feeFactor": "0.9961013694701175",
                "balAndRatioFactor": "0.96",
                "wrapFactor": "1",
                "valueUSD": "1.755788021611437341",
                "factorUSD": "1.678985138713325757"
            }
        ],
        "0x826976d7C600d45FB8287CA1d7c76FC8eb732030": [
            {
                "pool": "0xcd65f38b298310fa2c8b1844ea187016f913b0c8",
                "feeFactor": "0.9961013694701175",
                "balAndRatioFactor": "0.96",
                "wrapFactor": "1",
                "valueUSD": "278.824159573089947122",
                "factorUSD": "266.627642104425089977"
            }
        ],
        "0x830aD77c26c5E0fDBCD353Ac338Ec08053C1c02C": [
            {
                "pool": "0xcd65f38b298310fa2c8b1844ea187016f913b0c8",
                "feeFactor": "0.9961013694701175",
                "balAndRatioFactor": "0.96",
                "wrapFactor": "1",
                "valueUSD": "30.918417233013632812",
                "factorUSD": "29.565962637747226228"
            }
        ],
        "0x926f8b145E2210eD46b3E5258A96927bb56B5612": [
            {
                "pool": "0xcd65f38b298310fa2c8b1844ea187016f913b0c8",
                "feeFactor": "0.9961013694701175",
                "balAndRatioFactor": "0.96",
                "wrapFactor": "1",
                "valueUSD": "1211.924262609986906497",
                "factorUSD": "1158.911440972675464155"
            }
        ],
        "0x95577b29A69FBa8ed9373b9F194B6515A48A82dD": [
            {
                "pool": "0xcd65f38b298310fa2c8b1844ea187016f913b0c8",
                "feeFactor": "0.9961013694701175",
                "balAndRatioFactor": "0.96",
                "wrapFactor": "1",
                "valueUSD": "0.048761763996441594",
                "factorUSD": "0.046628793498848776"
            }
        ],
        "0x98C1265c08c81beE4a59E63e474C7E083ec74e15": [
            {
                "pool": "0xcd65f38b298310fa2c8b1844ea187016f913b0c8",
                "feeFactor": "0.9961013694701175",
                "balAndRatioFactor": "0.96",
                "wrapFactor": "1",
                "valueUSD": "589.933835414136532713",
                "factorUSD": "564.128545298669089976"
            }
        ],
        "0x9BDbdb4A8f7f816C87a67F5281484ED902C6b942": [
            {
                "pool": "0xcd65f38b298310fa2c8b1844ea187016f913b0c8",
                "feeFactor": "0.9961013694701175",
                "balAndRatioFactor": "0.96",
                "wrapFactor": "1",
                "valueUSD": "0.023329825271427456",
                "factorUSD": "0.022309316066272747"
            }
        ],
        "0xa06ea9cc58D0d50C033A1b55F1399fb6909b65AF": [
            {
                "pool": "0xcd65f38b298310fa2c8b1844ea187016f913b0c8",
                "feeFactor": "0.9961013694701175",
                "balAndRatioFactor": "0.96",
                "wrapFactor": "1",
                "valueUSD": "0.078608708237185005",
                "factorUSD": "0.075170152250243414"
            }
        ],
        "0xA298D0b6B9216f7d9EB252DeA06280b748eFe8E5": [
            {
                "pool": "0xcd65f38b298310fa2c8b1844ea187016f913b0c8",
                "feeFactor": "0.9961013694701175",
                "balAndRatioFactor": "0.96",
                "wrapFactor": "1",
                "valueUSD": "1549.158951797538908861",
                "factorUSD": "1481.39457927592344141"
            }
        ],
        "0xa2BfA5a2EA2E032A82E948dAD4310B069a9C8ED5": [
            {
                "pool": "0xcd65f38b298310fa2c8b1844ea187016f913b0c8",
                "feeFactor": "0.9961013694701175",
                "balAndRatioFactor": "0.96",
                "wrapFactor": "1",
                "valueUSD": "0.029743688734311163",
                "factorUSD": "0.028442619918086645"
            }
        ],
        "0xAABd5fBcb8ad62D4FbBB02a2E9769a9F2EE7e883": [
            {
                "pool": "0xcd65f38b298310fa2c8b1844ea187016f913b0c8",
                "feeFactor": "0.9961013694701175",
                "balAndRatioFactor": "0.96",
                "wrapFactor": "1",
                "valueUSD": "0.504894988709094384",
                "factorUSD": "0.482809526104059291"
            }
        ],
        "0xad7575AEFd4d64520c3269FD24eae1b0E13dbE7B": [
            {
                "pool": "0xcd65f38b298310fa2c8b1844ea187016f913b0c8",
                "feeFactor": "0.9961013694701175",
                "balAndRatioFactor": "0.96",
                "wrapFactor": "1",
                "valueUSD": "0.084113631565207981",
                "factorUSD": "0.08043427544948023"
            }
        ],
        "0xafD677bc7B527EBf4f51Def5d2C638104b6A83ce": [
            {
                "pool": "0xcd65f38b298310fa2c8b1844ea187016f913b0c8",
                "feeFactor": "0.9961013694701175",
                "balAndRatioFactor": "0.96",
                "wrapFactor": "1",
                "valueUSD": "78.661322571226359432",
                "factorUSD": "75.220465092028071315"
            }
        ],
        "0xB2938Bd4c7854C0709c2FefefE1284fb24133d19": [
            {
                "pool": "0xcd65f38b298310fa2c8b1844ea187016f913b0c8",
                "feeFactor": "0.9961013694701175",
                "balAndRatioFactor": "0.96",
                "wrapFactor": "1",
                "valueUSD": "29.560306915009809258",
                "factorUSD": "28.267259711998325027"
            }
        ],
        "0xBA333F8ff556bF35D38E102a98dAF1c5F6d9D708": [
            {
                "pool": "0xcd65f38b298310fa2c8b1844ea187016f913b0c8",
                "feeFactor": "0.9961013694701175",
                "balAndRatioFactor": "0.96",
                "wrapFactor": "1",
                "valueUSD": "0.672091112130789139",
                "factorUSD": "0.642692042114086428"
            }
        ],
        "0xBC1939b8b22D47Aff7119917c2E8eA241d1C367d": [
            {
                "pool": "0xcd65f38b298310fa2c8b1844ea187016f913b0c8",
                "feeFactor": "0.9961013694701175",
                "balAndRatioFactor": "0.96",
                "wrapFactor": "1",
                "valueUSD": "82.929034845858598974",
                "factorUSD": "79.30149617164305116"
            }
        ],
        "0xBd5f593C86319523e6E8AfE60dEdBEfaeDBdB8C9": [
            {
                "pool": "0xcd65f38b298310fa2c8b1844ea187016f913b0c8",
                "feeFactor": "0.9961013694701175",
                "balAndRatioFactor": "0.96",
                "wrapFactor": "1",
                "valueUSD": "0.058636586584812939",
                "factorUSD": "0.056071664830257877"
            }
        ],
        "0xCa42438C22a1BD26d48CC86aC669F23ead65e2c4": [
            {
                "pool": "0xcd65f38b298310fa2c8b1844ea187016f913b0c8",
                "feeFactor": "0.9961013694701175",
                "balAndRatioFactor": "0.96",
                "wrapFactor": "1",
                "valueUSD": "0.022503596386405162",
                "factorUSD": "0.021519228651360931"
            }
        ],
        "0xce66C6A88bD7BEc215Aa04FDa4CF7C81055521D0": [
            {
                "pool": "0xcd65f38b298310fa2c8b1844ea187016f913b0c8",
                "feeFactor": "0.9961013694701175",
                "balAndRatioFactor": "0.96",
                "wrapFactor": "1",
                "valueUSD": "3623.425774787817332111",
                "factorUSD": "3464.927401381887739888"
            }
        ],
        "0xd4DC77165051bc2AeAdFf2C8A681B87163E47820": [
            {
                "pool": "0xcd65f38b298310fa2c8b1844ea187016f913b0c8",
                "feeFactor": "0.9961013694701175",
                "balAndRatioFactor": "0.96",
                "wrapFactor": "1",
                "valueUSD": "495.688839911448857421",
                "factorUSD": "474.006078976174122094"
            }
        ],
        "0xd61b13A235EE8cfdef89337bb425D9323895c7Ea": [
            {
                "pool": "0xcd65f38b298310fa2c8b1844ea187016f913b0c8",
                "feeFactor": "0.9961013694701175",
                "balAndRatioFactor": "0.96",
                "wrapFactor": "1",
                "valueUSD": "0.627910048437279831",
                "factorUSD": "0.600443576786325362"
            }
        ],
        "0xDeBdaF2390372E715C7F396559d1BbE1b69B53AD": [
            {
                "pool": "0xcd65f38b298310fa2c8b1844ea187016f913b0c8",
                "feeFactor": "0.9961013694701175",
                "balAndRatioFactor": "0.96",
                "wrapFactor": "1",
                "valueUSD": "524.735486733846466681",
                "factorUSD": "501.782147467347013711"
            }
        ],
        "0xdec0DED0606B7d0560ADEBD6C3a919a671dB4D66": [
            {
                "pool": "0xcd65f38b298310fa2c8b1844ea187016f913b0c8",
                "feeFactor": "0.9961013694701175",
                "balAndRatioFactor": "0.96",
                "wrapFactor": "1",
                "valueUSD": "0",
                "factorUSD": "0"
            }
        ],
        "0xE2B52Fc1ad49B93F85C45315EcbAd740f17B0e8E": [
            {
                "pool": "0xcd65f38b298310fa2c8b1844ea187016f913b0c8",
                "feeFactor": "0.9961013694701175",
                "balAndRatioFactor": "0.96",
                "wrapFactor": "1",
                "valueUSD": "2947.728043814235976776",
                "factorUSD": "2818.786503618077737722"
            }
        ],
        "0xE380c7FE194cF2afE3477044D3c6F5D4f82343a7": [
            {
                "pool": "0xcd65f38b298310fa2c8b1844ea187016f913b0c8",
                "feeFactor": "0.9961013694701175",
                "balAndRatioFactor": "0.96",
                "wrapFactor": "1",
                "valueUSD": "16025.45155908389938599",
                "factorUSD": "15324.455274605281716067"
            }
        ],
        "0xE5A3D77D7788A83f3549dD7F08Fc2aCed7E262d2": [
            {
                "pool": "0xcd65f38b298310fa2c8b1844ea187016f913b0c8",
                "feeFactor": "0.9961013694701175",
                "balAndRatioFactor": "0.96",
                "wrapFactor": "1",
                "valueUSD": "12291.943509530927152378",
                "factorUSD": "11754.260892761355683678"
            }
        ],
        "0xF00F24f0e421317826487248612D77453bcC10fD": [
            {
                "pool": "0xcd65f38b298310fa2c8b1844ea187016f913b0c8",
                "feeFactor": "0.9961013694701175",
                "balAndRatioFactor": "0.96",
                "wrapFactor": "1",
                "valueUSD": "22.931846919129170765",
                "factorUSD": "21.928746355798715358"
            }
        ],
        "0xF3783A4f80B2e06A6addc58D4d69B3a04aC32971": [
            {
                "pool": "0xcd65f38b298310fa2c8b1844ea187016f913b0c8",
                "feeFactor": "0.9961013694701175",
                "balAndRatioFactor": "0.96",
                "wrapFactor": "1",
                "valueUSD": "34.222993487608894875",
                "factorUSD": "32.725987853159167548"
            }
        ],
        "0xfC67418ff4fFb7F39769587bFD425D750B9f0663": [
            {
                "pool": "0xcd65f38b298310fa2c8b1844ea187016f913b0c8",
                "feeFactor": "0.9961013694701175",
                "balAndRatioFactor": "0.96",
                "wrapFactor": "1",
                "valueUSD": "104.845228037936411065",
                "factorUSD": "100.25901622175541071"
            }
        ]
    },
    {
        "0x007De57773B6EB4ebbf6A740dFdE1EfDd5629630": "0.000023359488708691",
        "0x02FF537c4e2995d7ce0Be764fEa5B9fa5d782Cf5": "0.000033561892162717",
        "0x0dC437c879FaDa4Ac7E5554b0F8F1EE78343C26B": "0.004724799855220606",
        "0x12db4993126eBcd26E8dFeF76Fe3aE539b47f25b": "0.127475358091546553",
        "0x15eCd31318fa645B6496F1f21b22Ebfe3AD0c865": "0.005318034880059903",
        "0x169833EBB85FBD3cb67eeC73Ed02f738c0017951": "0.261893248426328816",
        "0x18fEe6e511646B8ea2e4964277574F637Bc03f3b": "0.100829194956098821",
        "0x1c85d6Ae1336D0e4E3F165bbfA9641bfA04CeDb1": "0.000164641150609262",
        "0x25a9b8B7Ff067DF3087fa015F91654360c26006C": "0.004252045332943219",
        "0x26b350F462Ae30EC1c48c36ba944AB66F06dAFee": "0.002405821215470964",
        "0x280A8675cF1d930c638F4f9Eb9dbe75823801D5a": "0.025977310894988092",
        "0x2b1DEE0c00322E99775f76B60b5bBB7b04d1dFc3": "0.000004288759168835",
        "0x2E78A0D97479cCb3238a4Cd5f373654bA09FEf2e": "0.000062716436211419",
        "0x343EF442adD9bd565D51b606f444F9221AD0Aeb6": "0.000038405517128713",
        "0x43a37B93b5930A978f325C426d38233Bc464cb5A": "0.045354211418402995",
        "0x48Fda4c03bec8D10ceCc2d088B329a796E5360b6": "0.00309741180128989",
        "0x4Cd0dCD8EB96E8F02273e9Ca02F2D937A3b48418": "0.006022640801632683",
        "0x4dddafFEa0C4D6fee5afe772EA48c3B70026C09F": "0.00308119056888158",
        "0x4ef416AA741053b5F3968900379DF2e3d0229065": "0",
        "0x4fFAD6ac852c0Af0AA301376F4C5Dea3a928b120": "0.027421713619576192",
        "0x4FfD0A59a26cB2Aa76D403215e4cC2845C053994": "0.001613093243997981",
        "0x50BBf827267C4E920B512F8aA6c1c9d1a465a128": "0.000077015746952752",
        "0x543F39508598e746978452Ce608b50a58A7455F2": "0.000062779187047433",
        "0x59b8C949D5eB9feE0ba981fc3FDAa9E5B64652CE": "0.000079302548146687",
        "0x689cC0Ea1140546a8a7985315E9C8fef7e0461bc": "3.534014498196072547",
        "0x6a1afc8a229d820015361Da64819e64E6A0258F9": "0.000051736215377962",
        "0x6AFBC428dcdE09679592B330a9164247E9614BD3": "0.014350100201536224",
        "0x6E0B6FF7536100a9e6b7041CA5a98108935932e5": "0.000100986186526217",
        "0x6Ff1dd1443289CC30aA3A010b6EF7BB4058D8C54": "0.000002585542443793",
        "0x751f556a157f8cb70d5f37086664b437F339D914": "0.001059790427482539",
        "0x7Ad5583713ca971F2aE1E0a894486a9406179eca": "0.000129470842736837",
        "0x7B72Cf70FD7Ce243b84AD2dC49EA44f970B95D42": "0.317234797313300225",
        "0x7E8416AD4DE6e12A807BC3A987ae53B0299C96Fb": "0.000093582375510893",
        "0x826976d7C600d45FB8287CA1d7c76FC8eb732030": "0.014861148886715958",
        "0x830aD77c26c5E0fDBCD353Ac338Ec08053C1c02C": "0.001647931809585428",
        "0x926f8b145E2210eD46b3E5258A96927bb56B5612": "0.064594785952718857",
        "0x95577b29A69FBa8ed9373b9F194B6515A48A82dD": "0.000002598970748581",
        "0x98C1265c08c81beE4a59E63e474C7E083ec74e15": "0.031443095084817061",
        "0x9BDbdb4A8f7f816C87a67F5281484ED902C6b942": "0.000001243464724824",
        "0xa06ea9cc58D0d50C033A1b55F1399fb6909b65AF": "0.000004189793734847",
        "0xA298D0b6B9216f7d9EB252DeA06280b748eFe8E5": "0.082569178607412202",
        "0xa2BfA5a2EA2E032A82E948dAD4310B069a9C8ED5": "0.000001585319533987",
        "0xAABd5fBcb8ad62D4FbBB02a2E9769a9F2EE7e883": "0.000026910579093465",
        "0xad7575AEFd4d64520c3269FD24eae1b0E13dbE7B": "0.000004483202617753",
        "0xafD677bc7B527EBf4f51Def5d2C638104b6A83ce": "0.004192598045115051",
        "0xB2938Bd4c7854C0709c2FefefE1284fb24133d19": "0.001575545400633842",
        "0xBA333F8ff556bF35D38E102a98dAF1c5F6d9D708": "0.000035822025243813",
        "0xBC1939b8b22D47Aff7119917c2E8eA241d1C367d": "0.004420064372337494",
        "0xBd5f593C86319523e6E8AfE60dEdBEfaeDBdB8C9": "0.000003125292459513",
        "0xCa42438C22a1BD26d48CC86aC669F23ead65e2c4": "0.000001199427255138",
        "0xce66C6A88bD7BEc215Aa04FDa4CF7C81055521D0": "0.193126269981530468",
        "0xd4DC77165051bc2AeAdFf2C8A681B87163E47820": "0.026419897266745013",
        "0xd61b13A235EE8cfdef89337bb425D9323895c7Ea": "0.000033467202883627",
        "0xDeBdaF2390372E715C7F396559d1BbE1b69B53AD": "0.027968064913868685",
        "0xdec0DED0606B7d0560ADEBD6C3a919a671dB4D66": "0",
        "0xE2B52Fc1ad49B93F85C45315EcbAd740f17B0e8E": "0.157112014266425328",
        "0xE380c7FE194cF2afE3477044D3c6F5D4f82343a7": "0.854146290483019663",
        "0xE5A3D77D7788A83f3549dD7F08Fc2aCed7E262d2": "0.655152705855663093",
        "0xF00F24f0e421317826487248612D77453bcC10fD": "0.001222252733889156",
        "0xF3783A4f80B2e06A6addc58D4d69B3a04aC32971": "0.001824063604628723",
        "0xfC67418ff4fFb7F39769587bFD425D750B9f0663": "0.005588183413944867"
    },
    {
        "0xe91D153E0b41518A2Ce8Dd3D7944Fa863463a97d": "47472.7611065459400914684",
        "0xC45b3C1c24d5F54E7a2cF288ac668c74Dd507a84": "71209.1416598189101372026"
    }
]